borja_package/calc.py
borja_package/const.py
borja_package2-0.0.1.dist-info/METADATA
borja_package2-0.0.1.dist-info/WHEEL
borja_package2-0.0.1.dist-info/licenses/LICENSE
borja_package2-0.0.1.dist-info/RECORD
