Metadata-Version: 2.1
Name: borja-package2
Version: 0.0.1
Summary: Ejemplo de como crear un paquete
Project-URL: Homepage, https://github.com/BorjaRei/prueba_pypi
Project-URL: Bug Tracker, https://github.com/BorjaRei/prueba_pypi/issues
Author-email: BorjaRei <borjareinoso@gmail.com>
License:                     GNU GENERAL PUBLIC LICENSE
License-File: LICENSE
Classifier: License :: OSI Approved :: GNU General Public License v3 (GPLv3)
Classifier: Operating System :: OS Independent
Classifier: Programming Language :: Python :: 3
Requires-Python: >=3.8
